windsong.py
windsong-0.1.2.dist-info/entry_points.txt
windsong-0.1.2.dist-info/WHEEL
windsong-0.1.2.dist-info/METADATA
windsong-0.1.2.dist-info/RECORD
