Metadata-Version: 2.1
Name: windsong
Version: 0.1.2
Summary: Transform MIDI files into keyboard keys for Genshin Impact instruments.
Home-page: https://github.com/ongyx/windsong
Author: Ong Yong Xin
Author-email: ongyongxin2020+github@gmail.com
Requires-Python: >=3.6
Classifier: Programming Language :: Python :: 3
Classifier: License :: OSI Approved :: MIT License
Classifier: Operating System :: OS Independent
Requires-Dist: mido>=1.2.9
Requires-Dist: pytest>=6.2.2 ; extra == "test"
Provides-Extra: test
